tools/__init__.py
tools/aws_security_hub_export.py
tools/format_findings.py
tools/gen-tests.py
tools/process_raw_response.py
tools/sort-ruleset.py
tools/utils.py
wpaudit/__init__.py
wpaudit/__main__.py
wpaudit/utils.py
wpaudit/core/__init__.py
wpaudit/core/cli_parser.py
wpaudit/core/conditions.py
wpaudit/core/console.py
wpaudit/core/exceptions.py
wpaudit/core/fs.py
wpaudit/core/processingengine.py
wpaudit/core/rule.py
wpaudit/core/rule_definition.py
wpaudit/core/ruleset.py
wpaudit/core/server.py
wpaudit/core/utils.py
wpaudit/data/icmp_message_types.json
wpaudit/data/protocols.json
wpaudit/data/aws/ip-ranges/aws-in-ec2.json
wpaudit/data/aws/ip-ranges/aws-in-us.json
wpaudit/data/aws/ip-ranges/aws.json
wpaudit/output/__init__.py
wpaudit/output/html.py
wpaudit/output/result_encoder.py
wpaudit/output/utils.py
wpaudit/output/data/includes.zip
wpaudit/output/data/html/report.html
wpaudit/output/data/html/conditionals/json_format.html
wpaudit/output/data/html/conditionals/sqlite_format.html
wpaudit/output/data/html/partials/about_wpaudit.html
wpaudit/output/data/html/partials/accordion.html
wpaudit/output/data/html/partials/accordion_policy.html
wpaudit/output/data/html/partials/count_badge.html
wpaudit/output/data/html/partials/dashboard.html
wpaudit/output/data/html/partials/details.html
wpaudit/output/data/html/partials/details_for_region.html
wpaudit/output/data/html/partials/details_for_vpc.html
wpaudit/output/data/html/partials/ec2_grants.html
wpaudit/output/data/html/partials/filters.html
wpaudit/output/data/html/partials/generic_object.html
wpaudit/output/data/html/partials/ip_grants.html
wpaudit/output/data/html/partials/last_run_details.html
wpaudit/output/data/html/partials/left_menu.html
wpaudit/output/data/html/partials/metadata.html
wpaudit/output/data/html/partials/modal.html
wpaudit/output/data/html/partials/network_interface.html
wpaudit/output/data/html/partials/policy.html
wpaudit-5.10.2.dist-info/DESCRIPTION.rst
wpaudit-5.10.2.dist-info/METADATA
wpaudit-5.10.2.dist-info/RECORD
wpaudit-5.10.2.dist-info/WHEEL
wpaudit-5.10.2.dist-info/entry_points.txt
wpaudit-5.10.2.dist-info/metadata.json
wpaudit-5.10.2.dist-info/top_level.txt
