Metadata-Version: 2.0
Name: wpaudit
Version: 5.10.2
Summary: WP Audit, a multi-cloud security auditing tool
Home-page: https://github.com/wperic/wpaudit
Author: Wembley Partners
License: GNU General Public License v2 (GPLv2)
Platform: UNKNOWN
Classifier: Development Status :: 5 - Production/Stable
Classifier: Intended Audience :: Developers
Classifier: Intended Audience :: Information Technology
Classifier: Intended Audience :: System Administrators
Classifier: Natural Language :: English
Classifier: License :: OSI Approved :: GNU General Public License v2 (GPLv2)
Classifier: Programming Language :: Python
Classifier: Programming Language :: Python :: 3
Classifier: Programming Language :: Python :: 3.6
Classifier: Programming Language :: Python :: 3.7
Classifier: Programming Language :: Python :: 3.8
Requires-Dist: PyJWT (==1.7.1)
Requires-Dist: adal (==1.2.4)
Requires-Dist: aliyun-python-sdk-actiontrail (>=2.0.0)
Requires-Dist: aliyun-python-sdk-core (>=2.13.4)
Requires-Dist: aliyun-python-sdk-ecs (>=4.16.10)
Requires-Dist: aliyun-python-sdk-kms (>=2.6.0)
Requires-Dist: aliyun-python-sdk-ocs (>=0.0.4)
Requires-Dist: aliyun-python-sdk-ram (>=3.0.1)
Requires-Dist: aliyun-python-sdk-rds (>=2.3.9)
Requires-Dist: aliyun-python-sdk-sts (>=3.0.1)
Requires-Dist: aliyun-python-sdk-vpc (>=3.0.5)
Requires-Dist: asyncio-throttle (==0.1.1)
Requires-Dist: azure-cli-core (==2.12.0)
Requires-Dist: azure-graphrbac (==0.61.1)
Requires-Dist: azure-mgmt-authorization (==0.60.0)
Requires-Dist: azure-mgmt-compute (==5.0.0)
Requires-Dist: azure-mgmt-keyvault (==1.1.0)
Requires-Dist: azure-mgmt-monitor (==0.5.2)
Requires-Dist: azure-mgmt-network (==2.5.1)
Requires-Dist: azure-mgmt-redis (==6.0.0)
Requires-Dist: azure-mgmt-security (==0.4.1)
Requires-Dist: azure-mgmt-sql (==0.11.0)
Requires-Dist: azure-mgmt-storage (==7.1.0)
Requires-Dist: azure-mgmt-web (==0.47.0)
Requires-Dist: boto3 (>=1.9.210)
Requires-Dist: botocore (>=1.12.210)
Requires-Dist: cherrypy-cors (>=1.6)
Requires-Dist: cherrypy (>=18.1.0)
Requires-Dist: coloredlogs (<=10.0)
Requires-Dist: google-api-python-client (>=1.7.8)
Requires-Dist: google-cloud-container (>=2.1.0)
Requires-Dist: google-cloud-core (>=0.29.1)
Requires-Dist: google-cloud-iam (>=0.1.0)
Requires-Dist: google-cloud-kms (==1.3.0)
Requires-Dist: google-cloud-logging (>=1.15.0)
Requires-Dist: google-cloud-monitoring (==1.1.0)
Requires-Dist: google-cloud-resource-manager (>=0.28.3)
Requires-Dist: google-cloud-storage (>=1.13.2)
Requires-Dist: grpcio (>=1.18.0)
Requires-Dist: httplib2shim (>=0.0.3)
Requires-Dist: netaddr (>=0.7.11)
Requires-Dist: oauth2client (>=4.1.3)
Requires-Dist: oci (>=2.2.4)
Requires-Dist: oss2 (>=2.8.0)
Requires-Dist: policyuniverse (>=1.3.2.0)
Requires-Dist: python-dateutil (<2.8.1,>=2.1)
Requires-Dist: sqlitedict (>=1.6.0)
